fancy_decorators/__init__.py
fancy_decorators/fancy_decorators.py
fancy_decorators-0.1.0.dist-info/AUTHORS.rst
fancy_decorators-0.1.0.dist-info/LICENSE
fancy_decorators-0.1.0.dist-info/METADATA
fancy_decorators-0.1.0.dist-info/WHEEL
fancy_decorators-0.1.0.dist-info/entry_points.txt
fancy_decorators-0.1.0.dist-info/top_level.txt
fancy_decorators-0.1.0.dist-info/RECORD
