Metadata-Version: 2.1
Name: fancy-decorators
Version: 0.1.0
Summary: Contains helpful decorators for common data-science tasks
Home-page: https://github.com/aadi350/fancy_decorators
Author: Aadidev Sooknanan
Author-email: a.aadi380@gmail.com
License: MIT license
Keywords: fancy_decorators
Platform: UNKNOWN
Classifier: Development Status :: 2 - Pre-Alpha
Classifier: Intended Audience :: Developers
Classifier: License :: OSI Approved :: MIT License
Classifier: Natural Language :: English
Classifier: Programming Language :: Python :: 3
Classifier: Programming Language :: Python :: 3.6
Classifier: Programming Language :: Python :: 3.7
Classifier: Programming Language :: Python :: 3.8
Requires-Python: >=3.6
